{
  "path": "../../src/modules/globals/views/localization/get-browser-locale.js",
  "relativePath": "modules/globals/views/localization/get-browser-locale.js",
  "type": "source",
  "name": "get-browser-locale.js",
  "extension": ".js",
  "analysis": {
    "Summary": "Функция для определения локали браузера и возврата её в виде строки.",
    "Purpose": "Обеспечить получение текущей локали пользователя из настроек браузера, с возможностью выбора только кода языка или полного кода с регионом.",
    "Components": [
      {
        "name": "getBrowserLocale",
        "type": "function",
        "responsibilities": "Определяет и возвращает локаль браузера с учётом переданных опций"
      }
    ],
    "Functions": [
      {
        "name": "getBrowserLocale",
        "description": "Возвращает строку локали браузера или undefined, если она не определена.",
        "parameters": [
          {
            "name": "options",
            "type": "object",
            "description": "Настройки вызова. Поддерживает поле countryCodeOnly (boolean), по умолчанию false."
          }
        ],
        "returns": "string | undefined"
      }
    ],
    "Dependencies": [
      "Глобальный объект navigator (navigator.languages, navigator.language)"
    ],
    "Usage": "Импортируется по умолчанию:\nimport getBrowserLocale from 'modules/globals/views/localization/get-browser-locale';\n\nПример вызова:\nconst locale = getBrowserLocale({ countryCodeOnly: true });",
    "Importance": 3,
    "Notes": [
      "Опции объединяются с дефолтными через оператор spread.",
      "При countryCodeOnly=true возвращается только часть до дефиса или подчёркивания.",
      "Если ни navigator.languages, ни navigator.language не заданы, возвращается undefined."
    ]
  }
}